rgf/VERSION
rgf/__init__.py
rgf/fastrgf_model.py
rgf/forest_predict.exe
rgf/forest_train.exe
rgf/rgf.exe
rgf/rgf_model.py
rgf/sklearn.py
rgf/utils.py
rgf_python-3.12.0.dist-info/LICENSE
rgf_python-3.12.0.dist-info/METADATA
rgf_python-3.12.0.dist-info/WHEEL
rgf_python-3.12.0.dist-info/top_level.txt
rgf_python-3.12.0.dist-info/RECORD
