Metadata-Version: 2.1
Name: rgf-python
Version: 3.12.0
Summary: Scikit-learn Wrapper for Regularized Greedy Forest
Home-page: https://github.com/RGF-team/rgf/tree/master/python-package
Author: RGF-team
Author-email: nannyakannya@gmail.com
License: MIT License
Keywords: Machine Learning
Platform: UNKNOWN
Classifier: Development Status :: 5 - Production/Stable
Classifier: Intended Audience :: Science/Research
Classifier: License :: OSI Approved :: MIT License
Classifier: Natural Language :: English
Classifier: Operating System :: MacOS
Classifier: Operating System :: Microsoft :: Windows
Classifier: Operating System :: POSIX
Classifier: Operating System :: Unix
Classifier: Programming Language :: Python :: 3
Classifier: Programming Language :: Python :: 3.7
Classifier: Programming Language :: Python :: 3.8
Classifier: Programming Language :: Python :: 3.9
Classifier: Topic :: Scientific/Engineering :: Artificial Intelligence
License-File: LICENSE
Requires-Dist: joblib
Requires-Dist: scikit-learn (>=0.18)
